llamacpp/__init__.py
llamacpp/chat.py
llamacpp/cli.py
llamacpp/convert.py
llamacpp/llamacpp.cp311-win_amd64.pyd
llamacpp/quantize.py
llamacpp-0.1.13.dist-info/METADATA
llamacpp-0.1.13.dist-info/WHEEL
llamacpp-0.1.13.dist-info/entry_points.txt
llamacpp-0.1.13.dist-info/RECORD
