Metadata-Version: 2.1
Name: llamacpp
Version: 0.1.13
Summary: Python bindings for @ggerganov's llama.cpp
Home-page: https://github.com/thomasantony/llamacpp-python
Author-Email: Thomas Antony <mail@thomasantony.com>
License: MIT
Classifier: Development Status :: 4 - Beta
Classifier: License :: OSI Approved :: MIT License
Classifier: Programming Language :: Python :: 3 :: Only
Classifier: Programming Language :: Python :: 3.7
Classifier: Programming Language :: Python :: 3.8
Classifier: Programming Language :: Python :: 3.9
Classifier: Programming Language :: Python :: 3.10
Classifier: Programming Language :: Python :: 3.11
Project-URL: Homepage, https://github.com/thomasantony/llamacpp-python
Project-URL: Repository, https://github.com/thomasantony/llamacpp-python
Requires-Python: >=3.7
